TSDataProcessing/TSDataProcessing.py
TSFeatures/TSFeatures.py
dscustom_libs-0.2.dist-info/LICENSE
dscustom_libs-0.2.dist-info/METADATA
dscustom_libs-0.2.dist-info/WHEEL
dscustom_libs-0.2.dist-info/top_level.txt
dscustom_libs-0.2.dist-info/RECORD
