Metadata-Version: 2.1
Name: dscustom-libs
Version: 0.2
Summary: Often used functions in Digital Smelter project
Home-page: https://github.com/luisgustavob78/dscustom-libs
Author: Luis Gustavo Silva Barros
Author-email: luisgustavob78@gmail.com
License: MIT
License-File: LICENSE
